freegs4e/__init__.py
freegs4e/_aeqdsk.py
freegs4e/_divgeo.py
freegs4e/_fileutils.py
freegs4e/_geqdsk.py
freegs4e/bilinear_interpolation.py
freegs4e/boundary.py
freegs4e/coil.py
freegs4e/control.py
freegs4e/critical.py
freegs4e/critical_old.py
freegs4e/divgeo.py
freegs4e/dump.py
freegs4e/equilibrium.py
freegs4e/fieldtracer.py
freegs4e/geqdsk.py
freegs4e/gradshafranov.py
freegs4e/jtor.py
freegs4e/machine.py
freegs4e/multi_coil.py
freegs4e/multigrid.py
freegs4e/optimise.py
freegs4e/optimiser.py
freegs4e/picard.py
freegs4e/plotting.py
freegs4e/polygons.py
freegs4e/quadrature.py
freegs4e/shaped_coil.py
freegs4e/test_aeqdsk.py
freegs4e/test_critical.py
freegs4e/test_equilibrium.py
freegs4e/test_fileutils.py
freegs4e/test_geqdsk.py
freegs4e/test_jtor.py
freegs4e/test_linearsolve.py
freegs4e/test_machine.py
freegs4e/test_multi_coil.py
freegs4e/test_optimise.py
freegs4e/test_optimiser.py
freegs4e/test_polygons.py
freegs4e/test_quadrature.py
freegs4e/test_readwrite.py
freegs4e/test_shaped_coil.py
freegs4e-0.12.0.dist-info/licenses/LICENSE
freegs4e-0.12.0.dist-info/METADATA
freegs4e-0.12.0.dist-info/WHEEL
freegs4e-0.12.0.dist-info/top_level.txt
freegs4e-0.12.0.dist-info/RECORD
